package com.zvm;

/**
 * 懒得写了，google了来源：
 * https://docs.atlassian.com/atlassian-plugins/2.5.5/atlassian-plugins-osgi/xref/com/atlassian/plugin/osgi/util/OpCodes.html
 * https://github.com/alibaba/atlas/blob/master/atlas-gradle-plugin/dexpatch/src/main/java/com/taobao/android/dx/cf/code/ByteOps.java
 */
public class Opcode {
    final static int	nop				= 0x00;
    final static int	aconst_null		= 0x01;
    final static int	iconst_m1		= 0x02;
    final static int	iconst_0		= 0x03;
    final static int	iconst_1		= 0x04;
    final static int	iconst_2		= 0x05;
    final static int	iconst_3		= 0x06;
    final static int	iconst_4		= 0x07;
    final static int	iconst_5		= 0x08;
    final static int	lconst_0		= 0x09;
    final static int	bipush			= 0x10;
    final static int	sipush			= 0x11;
    final static int	ldc				= 0x12;
    final static int	ldc_w			= 0x13;
    final static int	ldc2_w			= 0x14;
    final static int	iload			= 0x15;
    final static int	lload			= 0x16;
    final static int	fload			= 0x17;
    final static int	dload			= 0x18;
    final static int	aload			= 0x19;
    final static int	lload_2			= 0x20;
    final static int	lload_3			= 0x21;
    final static int	fload_0			= 0x22;
    final static int	fload_1			= 0x23;
    final static int	fload_2			= 0x24;
    final static int	fload_3			= 0x25;
    final static int	dload_0			= 0x26;
    final static int	dload_1			= 0x27;
    final static int	dload_2			= 0x28;
    final static int	dload_3			= 0x29;
    final static int	faload			= 0x30;
    final static int	daload			= 0x31;
    final static int	aaload			= 0x32;
    final static int	baload			= 0x33;
    final static int	caload			= 0x34;
    final static int	saload			= 0x35;
    final static int	istore			= 0x36;
    final static int	lstore			= 0x37;
    final static int	fstore			= 0x38;
    final static int	dstore			= 0x39;
    final static int	lstore_1		= 0x40;
    final static int	lstore_2		= 0x41;
    final static int	lstore_3		= 0x42;
    final static int	fstore_0		= 0x43;
    final static int	fstore_1		= 0x44;
    final static int	fstore_2		= 0x45;
    final static int	fstore_3		= 0x46;
    final static int	dstore_0		= 0x47;
    final static int	dstore_1		= 0x48;
    final static int	dstore_2		= 0x49;
    final static int	lastore			= 0x50;
    final static int	fastore			= 0x51;
    final static int	dastore			= 0x52;
    final static int	aastore			= 0x53;
    final static int	bastore			= 0x54;
    final static int	castore			= 0x55;
    final static int	sastore			= 0x56;
    final static int	pop				= 0x57;
    final static int	pop2			= 0x58;
    final static int	dup				= 0x59;
    final static int	iadd			= 0x60;
    final static int	ladd			= 0x61;
    final static int	fadd			= 0x62;
    final static int	dadd			= 0x63;
    final static int	isub			= 0x64;
    final static int	lsub			= 0x65;
    final static int	fsub			= 0x66;
    final static int	dsub			= 0x67;
    final static int	imul			= 0x68;
    final static int	lmul			= 0x69;
    final static int	irem			= 0x70;
    final static int	lrem			= 0x71;
    final static int	frem			= 0x72;
    final static int	drem			= 0x73;
    final static int	ineg			= 0x74;
    final static int	lneg			= 0x75;
    final static int	fneg			= 0x76;
    final static int	dneg			= 0x77;
    final static int	ishl			= 0x78;
    final static int	lshl			= 0x79;
    final static int	ior				= 0x80;
    final static int	lor				= 0x81;
    final static int	ixor			= 0x82;
    final static int	lxor			= 0x83;
    final static int	iinc			= 0x84;
    final static int	i2l				= 0x85;
    final static int	i2f				= 0x86;
    final static int	i2d				= 0x87;
    final static int	l2i				= 0x88;
    final static int	l2f				= 0x89;
    final static int	d2f				= 0x90;
    final static int	i2b				= 0x91;
    final static int	i2c				= 0x92;
    final static int	i2s				= 0x93;
    final static int	lcmp			= 0x94;
    final static int	fcmpl			= 0x95;
    final static int	fcmpg			= 0x96;
    final static int	dcmpl			= 0x97;
    final static int	dcmpg			= 0x98;
    final static int	ifeq			= 0x99;
    final static int	lconst_1		= 0x0a;
    final static int	fconst_0		= 0x0b;
    final static int	fconst_1		= 0x0c;
    final static int	fconst_2		= 0x0d;
    final static int	dconst_0		= 0x0e;
    final static int	dconst_1		= 0x0f;
    final static int	iload_0			= 0x1a;
    final static int	iload_1			= 0x1b;
    final static int	iload_2			= 0x1c;
    final static int	iload_3			= 0x1d;
    final static int	lload_0			= 0x1e;
    final static int	lload_1			= 0x1f;
    final static int	aload_0			= 0x2a;
    final static int	aload_1			= 0x2b;
    final static int	aload_2			= 0x2c;
    final static int	aload_3			= 0x2d;
    final static int	iaload			= 0x2e;
    final static int	laload			= 0x2f;
    final static int	astore			= 0x3a;
    final static int	istore_0		= 0x3b;
    final static int	istore_1		= 0x3c;
    final static int	istore_2		= 0x3d;
    final static int	istore_3		= 0x3e;
    final static int	lstore_0		= 0x3f;
    final static int	dstore_3		= 0x4a;
    final static int	astore_0		= 0x4b;
    final static int	astore_1		= 0x4c;
    final static int	astore_2		= 0x4d;
    final static int	astore_3		= 0x4e;
    final static int	iastore			= 0x4f;
    final static int	dup_x1			= 0x5a;
    final static int	dup_x2			= 0x5b;
    final static int	dup2			= 0x5c;
    final static int	dup2_x1			= 0x5d;
    final static int	dup2_x2			= 0x5e;
    final static int	swap			= 0x5f;
    final static int	fmul			= 0x6a;
    final static int	dmul			= 0x6b;
    final static int	idiv			= 0x6c;
    final static int	ldiv			= 0x6d;
    final static int	fdiv			= 0x6e;
    final static int	ddiv			= 0x6f;
    final static int	ishr			= 0x7a;
    final static int	lshr			= 0x7b;
    final static int	iushr			= 0x7c;
    final static int	lushr			= 0x7d;
    final static int	iand			= 0x7e;
    final static int	land			= 0x7f;
    final static int	l2d				= 0x8a;
    final static int	f2i				= 0x8b;
    final static int	f2l				= 0x8c;
    final static int	f2d				= 0x8d;
    final static int	d2i				= 0x8e;
    final static int	d2l				= 0x8f;
    final static int	ifne			= 0x9a;
    final static int	iflt			= 0x9b;
    final static int	ifge			= 0x9c;
    final static int	ifgt			= 0x9d;
    final static int	ifle			= 0x9e;
    final static int	if_icmpeq		= 0x9f;
    final static int	if_icmpne		= 0xa0;
    final static int	if_icmplt		= 0xa1;
    final static int	if_icmpge		= 0xa2;
    final static int	if_icmpgt		= 0xa3;
    final static int	if_icmple		= 0xa4;
    final static int	if_acmpeq		= 0xa5;
    final static int	if_acmpne		= 0xa6;
    final static int	goto_			= 0xa7;
    final static int	jsr				= 0xa8;
    final static int	ret				= 0xa9;
    final static int	tableswitch		= 0xaa;
    final static int	lookupswitch	= 0xab;
    final static int	ireturn			= 0xac;
    final static int	lreturn			= 0xad;
    final static int	freturn			= 0xae;
    final static int	dreturn			= 0xaf;
    final static int	areturn			= 0xb0;
    final static int	return_			= 0xb1;
    final static int	getstatic		= 0xb2;
    final static int	putstatic		= 0xb3;
    final static int	getfield		= 0xb4;
    final static int	putfield		= 0xb5;
    final static int	invokevirtual	= 0xb6;
    final static int	invokespecial	= 0xb7;
    final static int	invokestatic	= 0xb8;
    final static int	invokeinterface	= 0xb9;
    final static int	xxxunusedxxx	= 0xba;
    final static int	new_			= 0xbb;
    final static int	newarray		= 0xbc;
    final static int	anewarray		= 0xbd;
    final static int	arraylength		= 0xbe;
    final static int	athrow			= 0xbf;
    final static int	checkcast		= 0xc0;
    final static int	instanceof_		= 0xc1;
    final static int	monitorenter	= 0xc2;
    final static int	monitorexit		= 0xc3;
    final static int	wide			= 0xc4;
    final static int	multianewarray	= 0xc5;
    final static int	ifnull			= 0xc6;
    final static int	ifnonnull		= 0xc7;
    final static int	goto_w			= 0xc8;
    final static int	jsr_w			= 0xc9;
    final static int	breakpoint		= 0xca;
    /*final static int	impdep1			= 0xfe;*/
    final static int	invokenative	= 0xfe;
    final static int	impdep2			= 0xff;
}
