package com.zvm.interpreter;

/**
 * 懒得写了，google了来源：
 * https://docs.atlassian.com/atlassian-plugins/2.5.5/atlassian-plugins-osgi/xref/com/atlassian/plugin/osgi/util/OpCodes.html
 * https://github.com/alibaba/atlas/blob/master/atlas-gradle-plugin/dexpatch/src/main/java/com/taobao/android/dx/cf/code/ByteOps.java
 */
public class Opcode {
    final static int NOP = 0x00;
    final static int ACONST_NULL = 0x01;
    final static int ICONST_M1 = 0x02;
    final static int ICONST_0 = 0x03;
    final static int ICONST_1 = 0x04;
    final static int ICONST_2 = 0x05;
    final static int ICONST_3 = 0x06;
    final static int ICONST_4 = 0x07;
    final static int ICONST_5 = 0x08;
    final static int LCONST_0 = 0x09;
    final static int BIPUSH = 0x10;
    final static int SIPUSH = 0x11;
    final static int LDC = 0x12;
    final static int LDC_W = 0x13;
    final static int LDC2_W = 0x14;
    final static int ILOAD = 0x15;
    final static int LLOAD = 0x16;
    final static int FLOAD = 0x17;
    final static int DLOAD = 0x18;
    final static int ALOAD = 0x19;
    final static int LLOAD_2 = 0x20;
    final static int LLOAD_3 = 0x21;
    final static int FLOAD_0 = 0x22;
    final static int FLOAD_1 = 0x23;
    final static int FLOAD_2 = 0x24;
    final static int FLOAD_3 = 0x25;
    final static int DLOAD_0 = 0x26;
    final static int DLOAD_1 = 0x27;
    final static int DLOAD_2 = 0x28;
    final static int DLOAD_3 = 0x29;
    final static int FALOAD = 0x30;
    final static int DALOAD = 0x31;
    final static int AALOAD = 0x32;
    final static int BALOAD = 0x33;
    final static int CALOAD = 0x34;
    final static int SALOAD = 0x35;
    final static int ISTORE = 0x36;
    final static int LSTORE = 0x37;
    final static int FSTORE = 0x38;
    final static int DSTORE = 0x39;
    final static int LSTORE_1 = 0x40;
    final static int LSTORE_2 = 0x41;
    final static int LSTORE_3 = 0x42;
    final static int FSTORE_0 = 0x43;
    final static int FSTORE_1 = 0x44;
    final static int FSTORE_2 = 0x45;
    final static int FSTORE_3 = 0x46;
    final static int DSTORE_0 = 0x47;
    final static int DSTORE_1 = 0x48;
    final static int DSTORE_2 = 0x49;
    final static int LASTORE = 0x50;
    final static int FASTORE = 0x51;
    final static int DASTORE = 0x52;
    final static int AASTORE = 0x53;
    final static int BASTORE = 0x54;
    final static int CASTORE = 0x55;
    final static int SASTORE = 0x56;
    final static int POP = 0x57;
    final static int POP2 = 0x58;
    final static int DUP = 0x59;
    final static int IADD = 0x60;
    final static int LADD = 0x61;
    final static int FADD = 0x62;
    final static int DADD = 0x63;
    final static int ISUB = 0x64;
    final static int LSUB = 0x65;
    final static int FSUB = 0x66;
    final static int DSUB = 0x67;
    final static int IMUL = 0x68;
    final static int LMUL = 0x69;
    final static int IREM = 0x70;
    final static int LREM = 0x71;
    final static int FREM = 0x72;
    final static int DREM = 0x73;
    final static int INEG = 0x74;
    final static int LNEG = 0x75;
    final static int FNEG = 0x76;
    final static int DNEG = 0x77;
    final static int ISHL = 0x78;
    final static int LSHL = 0x79;
    final static int IOR = 0x80;
    final static int LOR = 0x81;
    final static int IXOR = 0x82;
    final static int LXOR = 0x83;
    final static int IINC = 0x84;
    final static int I2L = 0x85;
    final static int I2F = 0x86;
    final static int I2D = 0x87;
    final static int L2I = 0x88;
    final static int L2F = 0x89;
    final static int D2F = 0x90;
    final static int I2B = 0x91;
    final static int I2C = 0x92;
    final static int I2S = 0x93;
    final static int LCMP = 0x94;
    final static int FCMPL = 0x95;
    final static int FCMPG = 0x96;
    final static int DCMPL = 0x97;
    final static int DCMPG = 0x98;
    final static int IFEQ = 0x99;
    final static int LCONST_1 = 0x0a;
    final static int FCONST_0 = 0x0b;
    final static int FCONST_1 = 0x0c;
    final static int FCONST_2 = 0x0d;
    final static int DCONST_0 = 0x0e;
    final static int DCONST_1 = 0x0f;
    final static int ILOAD_0 = 0x1a;
    final static int ILOAD_1 = 0x1b;
    final static int ILOAD_2 = 0x1c;
    final static int ILOAD_3 = 0x1d;
    final static int LLOAD_0 = 0x1e;
    final static int LLOAD_1 = 0x1f;
    final static int ALOAD_0 = 0x2a;
    final static int ALOAD_1 = 0x2b;
    final static int ALOAD_2 = 0x2c;
    final static int ALOAD_3 = 0x2d;
    final static int IALOAD = 0x2e;
    final static int LALOAD = 0x2f;
    final static int ASTORE = 0x3a;
    final static int ISTORE_0 = 0x3b;
    final static int ISTORE_1 = 0x3c;
    final static int ISTORE_2 = 0x3d;
    final static int ISTORE_3 = 0x3e;
    final static int LSTORE_0 = 0x3f;
    final static int DSTORE_3 = 0x4a;
    final static int ASTORE_0 = 0x4b;
    final static int ASTORE_1 = 0x4c;
    final static int ASTORE_2 = 0x4d;
    final static int ASTORE_3 = 0x4e;
    final static int IASTORE = 0x4f;
    final static int DUP_X1 = 0x5a;
    final static int DUP_X2 = 0x5b;
    final static int DUP2 = 0x5c;
    final static int DUP2_X1 = 0x5d;
    final static int DUP2_X2 = 0x5e;
    final static int SWAP = 0x5f;
    final static int FMUL = 0x6a;
    final static int DMUL = 0x6b;
    final static int IDIV = 0x6c;
    final static int LDIV = 0x6d;
    final static int FDIV = 0x6e;
    final static int DDIV = 0x6f;
    final static int ISHR = 0x7a;
    final static int LSHR = 0x7b;
    final static int IUSHR = 0x7c;
    final static int LUSHR = 0x7d;
    final static int IAND = 0x7e;
    final static int LAND = 0x7f;
    final static int L2D = 0x8a;
    final static int F2I = 0x8b;
    final static int F2L = 0x8c;
    final static int F2D = 0x8d;
    final static int D2I = 0x8e;
    final static int D2L = 0x8f;
    final static int IFNE = 0x9a;
    final static int IFLT = 0x9b;
    final static int IFGE = 0x9c;
    final static int IFGT = 0x9d;
    final static int IFLE = 0x9e;
    final static int IF_ICMPEQ = 0x9f;
    final static int IF_ICMPNE = 0xa0;
    final static int IF_ICMPLT = 0xa1;
    final static int IF_ICMPGE = 0xa2;
    final static int IF_ICMPGT = 0xa3;
    final static int IF_ICMPLE = 0xa4;
    final static int IF_ACMPEQ = 0xa5;
    final static int IF_ACMPNE = 0xa6;
    final static int GOTO_ = 0xa7;
    final static int JSR = 0xa8;
    final static int RET = 0xa9;
    final static int TABLESWITCH = 0xaa;
    final static int LOOKUPSWITCH = 0xab;
    final static int IRETURN = 0xac;
    final static int LRETURN = 0xad;
    final static int FRETURN = 0xae;
    final static int DRETURN = 0xaf;
    final static int ARETURN = 0xb0;
    final static int RETURN_ = 0xb1;
    final static int GETSTATIC = 0xb2;
    final static int PUTSTATIC = 0xb3;
    final static int GETFIELD = 0xb4;
    final static int PUTFIELD = 0xb5;
    final static int INVOKEVIRTUAL = 0xb6;
    final static int INVOKESPECIAL = 0xb7;
    final static int INVOKESTATIC = 0xb8;
    final static int INVOKEINTERFACE = 0xb9;
    final static int XXXUNUSEDXXX = 0xba;
    final static int NEW_ = 0xbb;
    final static int NEWARRAY = 0xbc;
    final static int ANEWARRAY = 0xbd;
    final static int ARRAYLENGTH = 0xbe;
    final static int ATHROW = 0xbf;
    final static int CHECKCAST = 0xc0;
    final static int INSTANCEOF_ = 0xc1;
    final static int MONITORENTER = 0xc2;
    final static int MONITOREXIT = 0xc3;
    final static int WIDE = 0xc4;
    final static int MULTIANEWARRAY = 0xc5;
    final static int IFNULL = 0xc6;
    final static int IFNONNULL = 0xc7;
    final static int GOTO_W = 0xc8;
    final static int JSR_W = 0xc9;
    final static int BREAKPOINT = 0xca;
    /** final static int	impdep1			= 0xfe;*/
    final static int INVOKENATIVE = 0xfe;
    final static int IMPDEP2 = 0xff;
}
